LICENSE
vidpacktest/__init__.py
vidpacktest/cli.py
vidpacktest/constants.py
vidpacktest/core.py
vidpacktest/helpers.py
vidpacktest/utils.py
vidpacktest-0.1.14.dist-info/LICENSE
vidpacktest-0.1.14.dist-info/METADATA
vidpacktest-0.1.14.dist-info/WHEEL
vidpacktest-0.1.14.dist-info/entry_points.txt
vidpacktest-0.1.14.dist-info/RECORD
